[
    {
        "category_id": "9",
        "id": "22",
        "radio_image": "8841-2015-11-15.jpg",
        "radio_name": "Maestro Bandung FM",
        "radio_url": "http://192.99.170.8:5756/"
    },
    {
        "category_id": "4",
        "id": "24",
        "radio_image": "4548-2015-11-15.jpg",
        "radio_name": "Radio Jaca",
        "radio_url": "http://s6.voscast.com:8824"
    },
    {
        "category_id": "5",
        "id": "25",
        "radio_image": "3757-2015-11-15.jpg",
        "radio_name": "Radio Rama",
        "radio_url": "http://rama-fm.simaya.net.id:8800/"
    },
    {
        "category_id": "4",
        "id": "26",
        "radio_image": "5962-2015-11-15.jpg",
        "radio_name": "Radio Niagara",
        "radio_url": "http://s2.voscast.com:7386"
    },
    {
        "category_id": "7",
        "id": "29",
        "radio_image": "1593-2015-11-15.jpg",
        "radio_name": "Radio Rodja",
        "radio_url": "http://live.radiorodja.com/"
    },
    {
        "category_id": "8",
        "id": "30",
        "radio_image": "8896-2015-11-15.jpg",
        "radio_name": "Radio Zelengrad",
        "radio_url": "http://188.212.103.121:8000/"
    },
    {
        "category_id": "9",
        "id": "31",
        "radio_image": "0253-2015-11-15.jpg",
        "radio_name": "Suara Madu FM",
        "radio_url": "http://142.4.217.133:9228/stream"
    },
    {
        "category_id": "9",
        "id": "33",
        "radio_image": "7913-2017-11-07.jpg",
        "radio_name": "V Radio FM Jakarta",
        "radio_url": "http://193.0.98.66:8005"
    },
    {
        "category_id": "9",
        "id": "37",
        "radio_image": "0894-2019-05-03.jpg",
        "radio_name": "Radio 2.0 - Valli di Bergamo",
        "radio_url": "http://46.252.154.133:8080"
    }
]
